brainstat/__init__.py
brainstat/_typing.py
brainstat/_utils.py
brainstat/context/__init__.py
brainstat/context/genetics.py
brainstat/context/histology.py
brainstat/context/meta_analysis.py
brainstat/context/resting.py
brainstat/data/data_urls.json
brainstat/data/logging.conf
brainstat/data/nn_interp_civet164k.nii.gz
brainstat/data/nn_interp_civet41k.nii.gz
brainstat/data/nn_interp_fsaverage.nii.gz
brainstat/data/nn_interp_fsaverage5.nii.gz
brainstat/data/nn_interp_fslr32k.nii.gz
brainstat/datasets/__init__.py
brainstat/datasets/base.py
brainstat/mesh/__init__.py
brainstat/mesh/data.py
brainstat/mesh/interpolate.py
brainstat/mesh/utils.py
brainstat/stats/SLM.py
brainstat/stats/__init__.py
brainstat/stats/_linear_model.py
brainstat/stats/_multiple_comparisons.py
brainstat/stats/_t_test.py
brainstat/stats/terms.py
brainstat/stats/utils.py
brainstat/tests/__init__.py
brainstat/tests/conftest.py
brainstat/tests/datagen_f.py
brainstat/tests/datagen_fdr.py
brainstat/tests/datagen_linear_model.py
brainstat/tests/datagen_mesh_edges.py
brainstat/tests/datagen_mesh_smooth.py
brainstat/tests/datagen_peak_clus.py
brainstat/tests/datagen_random_field_theory.py
brainstat/tests/datagen_resels.py
brainstat/tests/datagen_slm.py
brainstat/tests/datagen_stat_threshold.py
brainstat/tests/datagen_t_test.py
brainstat/tests/test_SLM.py
brainstat/tests/test_datasets.py
brainstat/tests/test_f_test.py
brainstat/tests/test_fdr.py
brainstat/tests/test_genetics.py
brainstat/tests/test_histology.py
brainstat/tests/test_linear_model.py
brainstat/tests/test_mesh_edges.py
brainstat/tests/test_mesh_smooth.py
brainstat/tests/test_peak_clus.py
brainstat/tests/test_random_field_theory.py
brainstat/tests/test_resels.py
brainstat/tests/test_stat_threshold.py
brainstat/tests/test_t_test.py
brainstat/tests/test_terms.py
brainstat/tests/testutil.py
brainstat/tutorial/__init__.py
brainstat/tutorial/utils.py
brainstat-0.5.2.dist-info/licenses/LICENSE
brainstat-0.5.2.dist-info/METADATA
brainstat-0.5.2.dist-info/WHEEL
brainstat-0.5.2.dist-info/top_level.txt
brainstat-0.5.2.dist-info/RECORD
