Metadata-Version: 2.4
Name: brainstat
Version: 0.5.2
Summary: A toolbox for statistical analysis of neuroimaging data
Home-page: https://github.com/MICA-LAB/BrainStat
Author: MNI-MICA Lab and MPI-CNG Lab
Author-email: saratheriver@gmail.com, sheymaba@gmail.com
License: BSD 3-Clause License
Project-URL: Documentation, https://brainstat.readthedocs.io
Project-URL: Bug Reports, https://github.com/MICA-LAB/BrainStat/issues
Project-URL: Source, https://github.com/MICA-LAB/BrainStat/
Classifier: Intended Audience :: Science/Research
Classifier: Intended Audience :: Developers
Classifier: Topic :: Software Development :: Build Tools
Classifier: Topic :: Scientific/Engineering
Classifier: Programming Language :: Python :: 3.10
Requires-Python: >=3.10
License-File: LICENSE
Requires-Dist: abagen>=0.1
Requires-Dist: brainspace>=0.1.2
Requires-Dist: h5py
Requires-Dist: matplotlib>=3.4
Requires-Dist: netneurotools<0.3.0
Requires-Dist: neurosynth
Requires-Dist: nibabel
Requires-Dist: nilearn>=0.7.0
Requires-Dist: nimare
Requires-Dist: numpy>=1.21
Requires-Dist: pandas>=1.3
Requires-Dist: scikit_learn>=1.0
Requires-Dist: scipy>=1.7
Requires-Dist: templateflow
Requires-Dist: trimesh
Provides-Extra: dev
Requires-Dist: gitpython; extra == "dev"
Requires-Dist: hcp-utils; extra == "dev"
Requires-Dist: mypy; extra == "dev"
Requires-Dist: plotly; extra == "dev"
Requires-Dist: pytest; extra == "dev"
Dynamic: author
Dynamic: author-email
Dynamic: classifier
Dynamic: description
Dynamic: description-content-type
Dynamic: home-page
Dynamic: license
Dynamic: license-file
Dynamic: project-url
Dynamic: provides-extra
Dynamic: requires-dist
Dynamic: requires-python
Dynamic: summary
